dexhandpy/fdexhand.cpython-311-x86_64-linux-gnu.so
dexhandpy-0.1.13.dist-info/LICENSE.txt
dexhandpy-0.1.13.dist-info/METADATA
dexhandpy-0.1.13.dist-info/WHEEL
dexhandpy-0.1.13.dist-info/top_level.txt
dexhandpy-0.1.13.dist-info/RECORD
